ncr/__init__.py
ncr/__main__.py
ncr/colorformat.py
ncr/datastream.py
ncr/datastreamdiff.py
ncr/server.py
ncr/standard.py
ncr/summary.py
ncr/utils.py
ncr/version.py
ncr_web/.dockerignore
ncr_web/.eslintrc.json
ncr_web/.gitignore
ncr_web/.htaccess
ncr_web/Dockerfile
ncr_web/README.md
ncr_web/__init__.py
ncr_web/compose.yaml
ncr_web/ncreview.conf
ncr_web/package-lock.json
ncr_web/package.json
ncr_web/start-container.sh
ncr_web/tsconfig.json
ncr_web/build/asset-manifest.json
ncr_web/build/data.php
ncr_web/build/favicon-16x16.png
ncr_web/build/favicon-180x180.png
ncr_web/build/favicon-32x32.png
ncr_web/build/favicon-48x48.png
ncr_web/build/favicon.ico
ncr_web/build/index.html
ncr_web/build/manifest.json
ncr_web/build/ncreview.png
ncr_web/build/plotvar.php
ncr_web/build/robots.txt
ncr_web/build/static/js/main.75ae4e81.js
ncr_web/build/static/js/main.75ae4e81.js.LICENSE.txt
ncr_web/build/static/js/main.75ae4e81.js.map
ncr_web/public/data.php
ncr_web/public/favicon-16x16.png
ncr_web/public/favicon-180x180.png
ncr_web/public/favicon-32x32.png
ncr_web/public/favicon-48x48.png
ncr_web/public/favicon.ico
ncr_web/public/index.html
ncr_web/public/manifest.json
ncr_web/public/ncreview.png
ncr_web/public/plotvar.php
ncr_web/public/robots.txt
ncr_web/src/index.tsx
ncr_web/src/react-app-env.d.ts
ncr_web/src/setupProxy.js
ncr_web/src/setupTests.ts
ncr_web/src/components/ActionsSet.tsx
ncr_web/src/components/App.tsx
ncr_web/src/components/Bargraphs.tsx
ncr_web/src/components/D3Plot.jsx
ncr_web/src/components/DataTable.tsx
ncr_web/src/components/DataView.tsx
ncr_web/src/components/Header.tsx
ncr_web/src/components/Legend.tsx
ncr_web/src/components/LinkToOriginalNCR.tsx
ncr_web/src/components/Plot.tsx
ncr_web/src/components/PlotToolbar.tsx
ncr_web/src/components/Sections.tsx
ncr_web/src/components/StaticValue.tsx
ncr_web/src/components/StatusIndicator.tsx
ncr_web/src/components/Summaries.tsx
ncr_web/src/components/Timelines.tsx
ncr_web/src/components/UIComponents.tsx
ncreview_plus-0.0.2.dist-info/METADATA
ncreview_plus-0.0.2.dist-info/WHEEL
ncreview_plus-0.0.2.dist-info/entry_points.txt
ncreview_plus-0.0.2.dist-info/top_level.txt
ncreview_plus-0.0.2.dist-info/RECORD
