Metadata-Version: 2.2
Name: ncreview_plus
Version: 0.0.2
Summary: A tool to compare and/or summarize netCDF files
Author-email: Gabriel Gibler <gabriel.gibler@pnnl.gov>, Sherman Beus <sherman.beus@pnnl.gov>, Thomas Powell <thomas.powell@pnnl.gov>
License: MIT
Requires-Python: >=3.9
Requires-Dist: netCDF4
Requires-Dist: numpy==1.26
Requires-Dist: urllib3
Requires-Dist: act-atmos
Requires-Dist: matplotlib
